helpy/__init__.py
helpy/app.py
helpy/settings.py
helpy/commands/__init__.py
helpy/commands/pyhelp.py
helpy-1.0.1.data/scripts/helpy
helpy-1.0.1.dist-info/DESCRIPTION.rst
helpy-1.0.1.dist-info/entry_points.txt
helpy-1.0.1.dist-info/METADATA
helpy-1.0.1.dist-info/pydist.json
helpy-1.0.1.dist-info/RECORD
helpy-1.0.1.dist-info/top_level.txt
helpy-1.0.1.dist-info/WHEEL
