Metadata-Version: 2.0
Name: helpy
Version: 1.0.1
Summary: helpy displays built-in Python documentation from the command line.
Home-page: https://github.com/chrissimpkins/helpy
Author: Christopher Simpkins
Author-email: chris@zerolabs.net
License: MIT license
Keywords: python,help,documentation,built-in,command line,helpy
Platform: any
Classifier: Intended Audience :: Developers
Classifier: Programming Language :: Python :: Implementation :: PyPy
Classifier: Programming Language :: Python :: Implementation :: CPython
Classifier: Programming Language :: Python :: 3
Classifier: Programming Language :: Python :: 2
Classifier: Programming Language :: Python
Classifier: License :: OSI Approved :: MIT License
Requires-Dist: Naked
